<?xml version="1.0" encoding="utf-8"?>
<List xmlns:ows="Microsoft SharePoint" Title="Visitors" FolderCreation="FALSE" Direction="$Resources:Direction;" Url="Lists/Visitors" BaseType="0" xmlns="http://schemas.microsoft.com/sharepoint/">
  <MetaData>
    <ContentTypes>
      
      
    <ContentType ID="0x01009559654e7bd648ae838786c64f25aa08" Name="ListFieldsContentType"><FieldRefs><FieldRef ID="{fa564e0f-0c70-4ab9-b863-0177e6ddd247}" Name="Title" /><FieldRef ID="{d3096147-a5c0-48b3-9dbe-817abe1c55ec}" Name="Age" /><FieldRef ID="{23550288-91B5-4e7f-81F9-1A92661C4838}" Name="Gender" /></FieldRefs></ContentType><ContentTypeRef ID="0x01">
        <Folder TargetName="Item" />
      </ContentTypeRef><ContentTypeRef ID="0x0120" /></ContentTypes>
    <Fields>
      
    <Field ID="{fa564e0f-0c70-4ab9-b863-0177e6ddd247}" Type="Text" Name="Title" DisplayName="Full Name" Required="TRUE" SourceID="http://schemas.microsoft.com/sharepoint/v3" StaticName="Title" MaxLength="255" /><Field Name="Age" ID="{d3096147-a5c0-48b3-9dbe-817abe1c55ec}" DisplayName="Age" Type="Number" Required="TRUE" /><Field ID="{23550288-91B5-4e7f-81F9-1A92661C4838}" Name="Gender" StaticName="Gender" SourceID="http://schemas.microsoft.com/sharepoint/v3" DisplayName="$Resources:core,Gender_OL;" Group="$Resources:core,Person_Event_Columns;" Type="Choice" Sealed="TRUE" AllowDeletion="TRUE" Required="TRUE"><CHOICES><CHOICE>$Resources:core,Male;</CHOICE><CHOICE>$Resources:core,Female;</CHOICE></CHOICES></Field></Fields>
    <Views>
      
      
    <View BaseViewID="0" Type="HTML" MobileView="TRUE" TabularView="FALSE">
        <Toolbar Type="Standard" />
        <XslLink Default="TRUE">main.xsl</XslLink>
        <RowLimit Paged="TRUE">30</RowLimit>
        <ViewFields>
          
        <FieldRef Name="LinkTitleNoMenu"></FieldRef></ViewFields>
        <Query>
          <OrderBy>
            
          <FieldRef Name="Modified" Ascending="FALSE"></FieldRef></OrderBy>
        </Query>
        <ParameterBindings>
          <ParameterBinding Name="AddNewAnnouncement" Location="Resource(wss,addnewitem)" />
          <ParameterBinding Name="NoAnnouncements" Location="Resource(wss,noXinviewofY_LIST)" />
          <ParameterBinding Name="NoAnnouncementsHowTo" Location="Resource(wss,noXinviewofY_ONET_HOME)" />
        </ParameterBindings>
      </View><View BaseViewID="1" Type="HTML" WebPartZoneID="Main" DisplayName="$Resources:core,objectiv_schema_mwsidcamlidC24;" DefaultView="TRUE" MobileView="TRUE" MobileDefaultView="TRUE" SetupPath="pages\viewpage.aspx" ImageUrl="/_layouts/15/images/generic.png?rev=23" Url="AllItems.aspx">
        <Toolbar Type="Standard" />
        <XslLink Default="TRUE">main.xsl</XslLink>
        <JSLink>clienttemplates.js</JSLink>
        <RowLimit Paged="TRUE">30</RowLimit>
        <ViewFields>
          
        <FieldRef Name="LinkTitle"></FieldRef><FieldRef Name="Age" /><FieldRef Name="Gender" /></ViewFields>
        <Query>
          <OrderBy>
            
          <FieldRef Name="ID"></FieldRef></OrderBy>
        </Query>
        <ParameterBindings>
          <ParameterBinding Name="NoAnnouncements" Location="Resource(wss,noXinviewofY_LIST)" />
          <ParameterBinding Name="NoAnnouncementsHowTo" Location="Resource(wss,noXinviewofY_DEFAULT)" />
        </ParameterBindings>
      </View></Views>
    <Forms>
      <Form Type="DisplayForm" Url="DispForm.aspx" SetupPath="pages\form.aspx" WebPartZoneID="Main" />
      <Form Type="EditForm" Url="EditForm.aspx" SetupPath="pages\form.aspx" WebPartZoneID="Main" />
      <Form Type="NewForm" Url="NewForm.aspx" SetupPath="pages\form.aspx" WebPartZoneID="Main" />
    </Forms>
  </MetaData>
</List>